cliresms.py
cliresms-0.2.0.dist-info/top_level.txt
cliresms-0.2.0.dist-info/WHEEL
cliresms-0.2.0.dist-info/metadata.json
cliresms-0.2.0.dist-info/DESCRIPTION.rst
cliresms-0.2.0.dist-info/RECORD
cliresms-0.2.0.dist-info/entry_points.txt
cliresms-0.2.0.dist-info/METADATA
