Metadata-Version: 2.0
Name: cliresms
Version: 0.2.0
Summary: Send webtexts from the command line for Irish carriers
Home-page: https://github.com/russelldavies/cliresms
Author: Russell Davies
Author-email: russell@zeroflux.net
License: Apache v2
Keywords: console cli sms webtext
Platform: UNKNOWN
Provides-Extra: dev
Requires-Dist: check-manifest; extra == 'dev'
Provides-Extra: test
Requires-Dist: coverage; extra == 'test'
